setup.py
jdcloud_apim_sdk/__init__.py
jdcloud_apim_sdk/simpleclient.py
jdcloud_apim_sdk/simplerequest.py
jdcloud_apim_sdk.egg-info/PKG-INFO
jdcloud_apim_sdk.egg-info/SOURCES.txt
jdcloud_apim_sdk.egg-info/dependency_links.txt
jdcloud_apim_sdk.egg-info/requires.txt
jdcloud_apim_sdk.egg-info/top_level.txt
jdcloud_apim_sdk/core/__init__.py
jdcloud_apim_sdk/core/config.py
jdcloud_apim_sdk/core/const.py
jdcloud_apim_sdk/core/credential.py
jdcloud_apim_sdk/core/exception.py
jdcloud_apim_sdk/core/jdcloudclient.py
jdcloud_apim_sdk/core/jdcloudrequest.py
jdcloud_apim_sdk/core/logger.py
jdcloud_apim_sdk/core/parameterbuilder.py
jdcloud_apim_sdk/core/signer.py
jdcloud_apim_sdk/core/util.py
jdcloud_apim_sdk/core/version.py